tiddlywiki_parser/__init__.py
tiddlywiki_parser/readers.py
tiddlywiki_parser/tiddler.py
tiddlywiki_parser/tiddlywiki.py
tiddlywiki_parser/writiers.py
tiddlywiki_parser-2.1.0.dist-info/licenses/LICENSE
tiddlywiki_parser-2.1.0.dist-info/METADATA
tiddlywiki_parser-2.1.0.dist-info/WHEEL
tiddlywiki_parser-2.1.0.dist-info/entry_points.txt
tiddlywiki_parser-2.1.0.dist-info/top_level.txt
tiddlywiki_parser-2.1.0.dist-info/RECORD
