Metadata-Version: 2.4
Name: tiddlywiki_parser
Version: 2.1.0
Summary: Library to extract tiddlers from a tiddlywiki file.
Project-URL: Homepage, https://github.com/nephlm/tiddlywiki_parser
Project-URL: Repository, https://github.com/nephlm/tiddlywiki_parser
Project-URL: Issues, https://github.com/nephlm/tiddlywiki_parser/issues
Classifier: Programming Language :: Python :: 3
Classifier: License :: OSI Approved :: MIT License
Classifier: Operating System :: OS Independent
Requires-Python: >=3.8
License-File: LICENSE
Requires-Dist: beautifulsoup4>=4.8.0
Requires-Dist: requests>=2.22.0
Dynamic: license-file
